mathematica_mcp/__init__.py
mathematica_mcp/logger.py
mathematica_mcp/server.py
mathematica_mcp-0.1.6.dist-info/METADATA
mathematica_mcp-0.1.6.dist-info/WHEEL
mathematica_mcp-0.1.6.dist-info/entry_points.txt
mathematica_mcp-0.1.6.dist-info/licenses/LICENSE
mathematica_mcp-0.1.6.dist-info/RECORD
