Metadata-Version: 2.4
Name: mathematica_mcp
Version: 0.1.6
Summary: MCP server for WolframScript
Project-URL: Homepage, https://github.com/lars20070/mathematica-mcp
Project-URL: Repository, https://github.com/lars20070/mathematica-mcp
Project-URL: Issues, https://github.com/lars20070/mathematica-mcp/issues
Author-email: Lars Nilse <l.nilse@dunelm.org.uk>
License-File: LICENSE
Keywords: mathematica,mcp,model-context-protocol,wolframscript
Requires-Python: <3.13,>=3.12
Requires-Dist: fastmcp>=2.13.0.1
Requires-Dist: loguru>=0.7.3
Requires-Dist: pydantic-settings>=2.8.1
Requires-Dist: pydantic>=2.10.6
